webio_jupyterlab_provider/__init__.py
webio_jupyterlab_provider/_version.py
webio_jupyterlab_provider/labextension/build_log.json
webio_jupyterlab_provider/labextension/package.json
webio_jupyterlab_provider/labextension/static/dist_main_js.f3643a60de93343d7e17.js
webio_jupyterlab_provider/labextension/static/dist_main_js.f3643a60de93343d7e17.js.map
webio_jupyterlab_provider/labextension/static/remoteEntry.b721c0ce59d5f7c6973f.js
webio_jupyterlab_provider/labextension/static/remoteEntry.b721c0ce59d5f7c6973f.js.map
webio_jupyterlab_provider/labextension/static/remoteEntry.c6cffd5f0231136fa9b6.js
webio_jupyterlab_provider/labextension/static/remoteEntry.c6cffd5f0231136fa9b6.js.map
webio_jupyterlab_provider/labextension/static/style.js
webio_jupyterlab_provider-0.1.0.data/data/share/jupyter/labextensions/webio-jupyterlab-provider/build_log.json
webio_jupyterlab_provider-0.1.0.data/data/share/jupyter/labextensions/webio-jupyterlab-provider/install.json
webio_jupyterlab_provider-0.1.0.data/data/share/jupyter/labextensions/webio-jupyterlab-provider/package.json
webio_jupyterlab_provider-0.1.0.data/data/share/jupyter/labextensions/webio-jupyterlab-provider/static/dist_main_js.f3643a60de93343d7e17.js
webio_jupyterlab_provider-0.1.0.data/data/share/jupyter/labextensions/webio-jupyterlab-provider/static/dist_main_js.f3643a60de93343d7e17.js.map
webio_jupyterlab_provider-0.1.0.data/data/share/jupyter/labextensions/webio-jupyterlab-provider/static/remoteEntry.c6cffd5f0231136fa9b6.js
webio_jupyterlab_provider-0.1.0.data/data/share/jupyter/labextensions/webio-jupyterlab-provider/static/remoteEntry.c6cffd5f0231136fa9b6.js.map
webio_jupyterlab_provider-0.1.0.data/data/share/jupyter/labextensions/webio-jupyterlab-provider/static/style.js
webio_jupyterlab_provider-0.1.0.dist-info/LICENSE
webio_jupyterlab_provider-0.1.0.dist-info/METADATA
webio_jupyterlab_provider-0.1.0.dist-info/WHEEL
webio_jupyterlab_provider-0.1.0.dist-info/top_level.txt
webio_jupyterlab_provider-0.1.0.dist-info/RECORD
